agent_build_sdk/__init__.py
agent_build_sdk/builder.py
agent_build_sdk/example/__init__.py
agent_build_sdk/example/prompts.py
agent_build_sdk/example/spy_agent.py
agent_build_sdk/example/test.py
agent_build_sdk/llms/__init__.py
agent_build_sdk/memory/__init__.py
agent_build_sdk/memory/memory.py
agent_build_sdk/model/__init__.py
agent_build_sdk/model/model.py
agent_build_sdk/model/roles.py
agent_build_sdk/model/werewolf_model.py
agent_build_sdk/sdk/__init__.py
agent_build_sdk/sdk/agent.py
agent_build_sdk/sdk/role_agent.py
agent_build_sdk/sdk/werewolf_agent.py
agent_build_sdk/server/__init__.py
agent_build_sdk/server/server.py
agent_build_sdk/utils/__init__.py
agent_build_sdk/utils/config.py
agent_build_sdk/utils/logger.py
agent_build_sdk/utils/net.py
werewolf_agent_build_sdk-0.0.11.dist-info/METADATA
werewolf_agent_build_sdk-0.0.11.dist-info/WHEEL
werewolf_agent_build_sdk-0.0.11.dist-info/top_level.txt
werewolf_agent_build_sdk-0.0.11.dist-info/RECORD
