Metadata-Version: 2.2
Name: werewolf-agent-build-sdk
Version: 0.0.11
Summary: werewolf-agent-agent-build-sdk
Home-page: 
Author: maodao
Author-email: zhengjianhui.zjh@taobao.com
License: BSD License
Platform: all
Classifier: Programming Language :: Python :: 3
Classifier: Programming Language :: Python :: 3.6
Classifier: Programming Language :: Python :: 3.7
Classifier: Programming Language :: Python :: 3.8
Classifier: Programming Language :: Python :: 3.9
Classifier: Programming Language :: Python :: 3.10
Classifier: Programming Language :: Python :: Implementation :: CPython
Classifier: Programming Language :: Python :: Implementation :: PyPy
Requires-Python: >=3.2
Requires-Dist: requests==2.31.0
Requires-Dist: retry==0.9.2
Requires-Dist: FastAPI==0.110.1
Requires-Dist: uvicorn==0.29.0
Requires-Dist: jsonpath==0.82.2
Requires-Dist: contextvars==2.4
Requires-Dist: langchain==0.0.291
Requires-Dist: markdown2
Dynamic: author
Dynamic: author-email
Dynamic: classifier
Dynamic: description
Dynamic: description-content-type
Dynamic: license
Dynamic: platform
Dynamic: requires-dist
Dynamic: requires-python
Dynamic: summary
